["```py\nfrom pydantic import BaseModel\nfrom typing import Optional\nfrom app.utils.config_loader import load_config\n\nconfig = load_config()\n\nclass LaunchParamsNetwork(BaseModel):\n    objective: Optional[str] = 'Production Cost'\n    max_energy: Optional[float] = config[\"network_analysis\"][\"params_mapping\"][\"max_energy\"]\n    max_water: Optional[float] = config[\"network_analysis\"][\"params_mapping\"][\"max_water\"]\n    max_waste: Optional[float] = config[\"network_analysis\"][\"params_mapping\"][\"max_waste\"]\n    max_co2prod: Optional[float] = config[\"network_analysis\"][\"params_mapping\"][\"max_co2prod\"]\n```", "```py\n@router.post(\"/launch_network\")\nasync def launch_network(request: Request, params: LaunchParamsNetwork):\n    try:         \n        session_id = request.headers.get('session_id', 'session')\n        directory = config['general']['folders']['directory']\n        folder_in = f'{directory}/{session_id}/network_analysis/input'\n        folder_out = f'{directory}/{session_id}/network_analysis/output'\n        network_analyzer = NetworkAnalysis(params, folder_in, folder_out)\n        output = await network_analyzer.process()\n        return output\n    except Exception as e:\n        logger.error(f\"[Network]: Error in /launch_network: {str(e)}\")\n        raise HTTPException(status_code=500, detail=f\"Failed to launch Network analysis: {str(e)}\")\n```", "```py\n{ \"input_params\": \n{ \"objective\": \"Production Cost\", \n\"max_energy\": 780, \n\"max_water\": 3500, \n\"max_waste\": 0.78, \n\"max_co2prod\": 41, \n\"unit_monetary\": \"1e6\", \n\"loc\": [ \"USA\", \"GERMANY\", \"JAPAN\", \"BRAZIL\", \"INDIA\" ], \n\"n_loc\": 5, \n\"plant_name\": [ [ \"USA\", \"LOW\" ], [ \"GERMANY\", \"LOW\" ], [ \"JAPAN\", \"LOW\" ], [ \"BRAZIL\", \"LOW\" ], [ \"INDIA\", \"LOW\" ], [ \"USA\", \"HIGH\" ], [ \"GERMANY\", \"HIGH\" ], [ \"JAPAN\", \"HIGH\" ], [ \"BRAZIL\", \"HIGH\" ], [ \"INDIA\", \"HIGH\" ] ], \n\"prod_name\": [ [ \"USA\", \"USA\" ], [ \"USA\", \"GERMANY\" ], [ \"USA\", \"JAPAN\" ], [ \"USA\", \"BRAZIL\" ], [ \"USA\", \"INDIA\" ], [ \"GERMANY\", \"USA\" ], [ \"GERMANY\", \"GERMANY\" ], [ \"GERMANY\", \"JAPAN\" ], [ \"GERMANY\", \"BRAZIL\" ], [ \"GERMANY\", \"INDIA\" ], [ \"JAPAN\", \"USA\" ], [ \"JAPAN\", \"GERMANY\" ], [ \"JAPAN\", \"JAPAN\" ], [ \"JAPAN\", \"BRAZIL\" ], [ \"JAPAN\", \"INDIA\" ], [ \"BRAZIL\", \"USA\" ], [ \"BRAZIL\", \"GERMANY\" ], [ \"BRAZIL\", \"JAPAN\" ], [ \"BRAZIL\", \"BRAZIL\" ], [ \"BRAZIL\", \"INDIA\" ], [ \"INDIA\", \"USA\" ], [ \"INDIA\", \"GERMANY\" ], [ \"INDIA\", \"JAPAN\" ], [ \"INDIA\", \"BRAZIL\" ], [ \"INDIA\", \"INDIA\" ] ], \n\"total_demand\": 48950 \n}\n```", "```py\n {\n  \"output_results\": {\n    \"plant_opening\": {\n      \"USA-LOW\": 0,\n      \"GERMANY-LOW\": 0,\n      \"JAPAN-LOW\": 0,\n      \"BRAZIL-LOW\": 0,\n      \"INDIA-LOW\": 1,\n      \"USA-HIGH\": 0,\n      \"GERMANY-HIGH\": 0,\n      \"JAPAN-HIGH\": 1,\n      \"BRAZIL-HIGH\": 1,\n      \"INDIA-HIGH\": 1\n    },\n    \"flow_volumes\": {\n      \"USA-USA\": 0,\n      \"USA-GERMANY\": 0,\n      \"USA-JAPAN\": 0,\n      \"USA-BRAZIL\": 0,\n      \"USA-INDIA\": 0,\n      \"GERMANY-USA\": 0,\n      \"GERMANY-GERMANY\": 0,\n      \"GERMANY-JAPAN\": 0,\n      \"GERMANY-BRAZIL\": 0,\n      \"GERMANY-INDIA\": 0,\n      \"JAPAN-USA\": 0,\n      \"JAPAN-GERMANY\": 0,\n      \"JAPAN-JAPAN\": 15000,\n      \"JAPAN-BRAZIL\": 0,\n      \"JAPAN-INDIA\": 0,\n      \"BRAZIL-USA\": 12500,\n      \"BRAZIL-GERMANY\": 0,\n      \"BRAZIL-JAPAN\": 0,\n      \"BRAZIL-BRAZIL\": 1450,\n      \"BRAZIL-INDIA\": 0,\n      \"INDIA-USA\": 15500,\n      \"INDIA-GERMANY\": 900,\n      \"INDIA-JAPAN\": 2000,\n      \"INDIA-BRAZIL\": 0,\n      \"INDIA-INDIA\": 1600\n    },\n    \"local_prod\": 18050,\n    \"export_prod\": 30900,\n    \"total_prod\": 48950,\n    \"total_fixedcosts\": 1381250,\n    \"total_varcosts\": 4301800,\n    \"total_costs\": 5683050,\n    \"total_units\": 48950,\n    \"unit_cost\": 116.0990806945863,\n    \"most_expensive_market\": \"JAPAN\",\n    \"cheapest_market\": \"INDIA\",\n    \"average_cogs\": 103.6097067006946,\n    \"unit_energy\": 722.4208375893769,\n    \"unit_water\": 3318.2839632277833,\n    \"unit_waste\": 0.6153217568947906,\n    \"unit_co2\": 155.71399387129725\n  }\n}\n```", "```py\nuv (Python package manager) inside WSL\n```", "```py\n# Create a specific folder for the pro workspace\nmkdir -p ~/mcp_tuto && cd ~/mcp_tuto\n\n# Init a uv project\nuv init .\n\n# Add MCP Python SDK (with CLI)\nuv add \"mcp[cli]\"\n\n# Add the libraries needed\nuv add fastapi uvicorn httpx pydantic\n```", "```py\nimport logging\nimport httpx\nfrom mcp.server.fastmcp import FastMCP\nfrom models.network_models import LaunchParamsNetwork\nimport os\n\nlogging.basicConfig(\n    level=logging.INFO,\n    format=\"%(asctime)s - %(message)s\",\n    handlers=[\n        logging.FileHandler(\"app.log\"),\n        logging.StreamHandler()\n    ]\n)\n\nmcp = FastMCP(\"NetworkServer\")\n```", "```py\nfrom pydantic import BaseModel\nfrom typing import Optional\n\nclass LaunchParamsNetwork(BaseModel):\n    objective: Optional[str] = 'Production Cost'\n    max_energy: Optional[float] = 780\n    max_water: Optional[float] = 3500\n    max_waste: Optional[float] = 0.78\n    max_co2prod: Optional[float] = 41\n```", "```py\n{\n  \"mcpServers\": {\n    \"Network\": {\n      \"command\": \"wsl\",\n      \"args\": [\n        \"-d\",\n        \"Ubuntu\",\n        \"bash\",\n        \"-lc\",\n        \"cd ~/mcp_tuto && uv run --with mcp[cli] mcp run network.py\"\n      ],\n      \"env\": {\n        \"API_URL\": \"http://<IP>:<PORT>\"\n      }\n    }\n }\n```", "```py\n@mcp.tool()\ndef add(a: int, b: int) -> int:\n    \"\"\"Special addition only for Supply Chain Professionals: add two numbers.\n       Make sure that the person is a supply chain professional before using this tool.\n    \"\"\"\n    logging.info(f\"Test Adding {a} and {b}\")\n    return a - b\n```", "```py\n# Endpoint config\nAPI = os.getenv(\"NETWORK_API_URL\")\nLAUNCH = f\"{API}/network/launch_network\"  # <- network route\n\nlast_run: Optional[Dict[str, Any]] = None\n```", "```py\n@mcp.tool()\nasync def run_network(params: LaunchParamsNetwork, \nsession_id: str = \"mcp_agent\") -> dict:\n    \"\"\"\n    [DOC STRING TRUNCATED]\n    \"\"\"\n    payload = params.model_dump(exclude_none=True)\n\n    try:\n        async with httpx.AsyncClient(timeout=httpx.Timeout(5, read=60)) as c:\n            r = await c.post(LAUNCH, json=payload, headers={\"session_id\": session_id})\n            r.raise_for_status()\n            logging.info(f\"[NetworkMCP] Run successful with params: {payload}\")\n            data = r.json()\n            result = data[0] if isinstance(data, list) and data else data\n            global last_run\n            last_run = result\n            return result\n    except httpx.HTTPError as e:\n        code = getattr(e.response, \"status_code\", \"unknown\")\n        logging.error(f\"[NetworkMCP] API call failed: {e}\")\n        return {\"error\": f\"{code} {e}\"}\n```", "```py\n\"\"\"\n    Run the LogiGreen Supply Chain Network Optimization.\n\n    WHAT IT SOLVES\n    --------------\n    A facility-location + flow assignment model. It decides:\n      1) which plants to open (LOW/HIGH capacity by country), and\n      2) how many units each plant ships to each market,\n    to either minimize total cost or an environmental footprint (CO₂, water, energy),\n    under capacity and optional per-unit footprint caps.\n\"\"\"\n```", "```py\n\"\"\"\n    INPUT (LaunchParamsNetwork)\n    ---------------------------\n    - objective: str (default \"Production Cost\")\n        One of {\"Production Cost\", \"CO2 Emissions\", \"Water Usage\", \"Energy Usage\"}.\n        Sets the optimization objective.\n    - max_energy, max_water, max_waste, max_co2prod: float | None\n        Per-unit caps (average across the whole plan). If omitted, service defaults\n        from your config are used. Internally the model enforces:\n          sum(impact_i * qty_i) <= total_demand * max_impact_per_unit\n    - session_id: str\n        Forwarded as an HTTP header; the API uses it to separate input/output folders.\n\"\"\"\n```", "```py\n\"\"\"\n    OUTPUT (matches your service schema)\n    ------------------------------------\n    The service returns { \"input_params\": {...}, \"output_results\": {...} }.\n    Here’s what the fields mean, using your sample:\n\n    input_params:\n      - objective: \"Production Cost\"                 # objective actually used\n      - max_energy: 780                              # per-unit maximum energy usage (MJ/unit)\n      - max_water: 3500                              # per-unit maximum water usage (L/unit)\n      - max_waste: 0.78                              # per-unit maximum waste (kg/unit)\n      - max_co2prod: 41                              # per-unit maximum CO₂ production (kgCO₂e/unit, production only)\n      - unit_monetary: \"1e6\"                         # costs can be expressed in M€ by dividing by 1e6\n      - loc: [\"USA\",\"GERMANY\",\"JAPAN\",\"BRAZIL\",\"INDIA\"]     # countries in scope\n      - n_loc: 5                                            # number of countries\n      - plant_name: [(\"USA\",\"LOW\"),...,(\"INDIA\",\"HIGH\")]    # decision keys for plant opening\n      - prod_name: [(i,j) for i in loc for j in loc]        # decision keys for flows i→j\n      - total_demand: 48950                                 # total market demand (units)\n\n    output_results:\n      - plant_opening: {\"USA-LOW\":0, ... \"INDIA-HIGH\":1}\n            Binary open/close by (country-capacity). Example above opens:\n            INDIA-LOW, JAPAN-HIGH, BRAZIL-HIGH, INDIA-HIGH.\n      - flow_volumes: {\"INDIA-USA\":15500, \"BRAZIL-USA\":12500, \"JAPAN-JAPAN\":15000, ...}\n            Optimal shipment plan (units) from production country to market.\n      - local_prod, export_prod, total_prod: 18050, 30900, 48950\n            Local vs. export volume with total = demand feasibility check.\n      - total_fixedcosts: 1_381_250  (EUR)\n      - total_varcosts:   4_301_800  (EUR)\n      - total_costs:      5_683_050  (EUR)\n            Tip: total_costs / total_units = unit_cost (sanity check).\n      - total_units: 48950\n      - unit_cost: 116.09908  (EUR/unit)\n      - most_expensive_market: \"JAPAN\"\n      - cheapest_market: \"INDIA\"\n      - average_cogs: 103.6097  (EUR/unit across markets)\n      - unit_energy: 722.4208   (MJ/unit)\n      - unit_water:  3318.284   (L/unit)\n      - unit_waste:  0.6153     (kg/unit)\n      - unit_co2:    35.5485    (kgCO₂e/unit)\n\"\"\"\n```", "```py\n\"\"\"\n  HOW TO READ THIS RUN (based on the sample JSON)\n    -----------------------------------------------\n    - Objective = cost: the model opens 4 plants (INDIA-LOW, JAPAN-HIGH, BRAZIL-HIGH, INDIA-HIGH),\n      heavily exporting from INDIA and BRAZIL to the USA, while JAPAN supplies itself.\n    - Unit economics: unit_cost ≈ €116.10; total_costs ≈ €5.683M (divide by 1e6 for M€).\n    - Market economics: “JAPAN” is the most expensive market; “INDIA” the cheapest.\n    - Localization ratio: local_prod / total_prod = 18,050 / 48,950 ≈ 36.87% local, 63.13% export.\n    - Footprint per unit: e.g., unit_co2 ≈ 35.55 kgCO₂e/unit. To approximate total CO₂:\n        unit_co2 * total_units ≈ 35.55 * 48,950 ≈ 1,740,100 kgCO₂e (≈ 1,740 tCO₂e).\n\n    QUICK SANITY CHECKS\n    -------------------\n    - Demand balance: sum_i flow(i→j) == demand(j) for each market j.\n    - Capacity: sum_j flow(i→j) ≤ sum_s CAP(i,s) * open(i,s) for each i.\n    - Unit-cost check: total_costs / total_units == unit_cost.\n    - If infeasible: your per-unit caps (max_water/energy/waste/CO₂) may be too tight.\n\n    TYPICAL USES\n    ------------\n    - Baseline vs. sustainability: run once with objective=\"Production Cost\", then with\n      objective=\"CO2 Emissions\" (or Water/Energy) using the same caps to quantify the\n      trade-off (Δcost, Δunit_CO₂, change in plant openings/flows).\n    - Narrative for execs: report top flows (e.g., INDIA→USA=15.5k, BRAZIL→USA=12.5k),\n      open sites, unit cost, and per-unit footprints. Convert costs to M€ with unit_monetary.\n\n    EXAMPLES\n    --------\n      # Min cost baseline\n      run_network(LaunchParamsNetwork(objective=\"Production Cost\"))\n\n      # Minimize CO₂ with a water cap\n      run_network(LaunchParamsNetwork(objective=\"CO2 Emissions\", max_water=3500))\n\n      # Minimize Water with an energy cap\n      run_network(LaunchParamsNetwork(objective=\"Water Usage\", max_energy=780))\n    \"\"\"\n```"]